setup.cfg
setup.py
labsuite/__init__.py
labsuite.egg-info/PKG-INFO
labsuite.egg-info/SOURCES.txt
labsuite.egg-info/dependency_links.txt
labsuite.egg-info/not-zip-safe
labsuite.egg-info/pbr.json
labsuite.egg-info/requires.txt
labsuite.egg-info/top_level.txt
labsuite/compilers/__init__.py
labsuite/compilers/compiler.py
labsuite/compilers/pfusx.py
labsuite/compilers/data/pFusX.db
labsuite/compilers/templates/pfusx.json
labsuite/config/containers/legacy_containers.json
labsuite/config/containers/microplates/24.yml
labsuite/config/containers/microplates/384.yml
labsuite/config/containers/microplates/96.yml
labsuite/config/containers/tipracks/1000ul.yml
labsuite/config/containers/tipracks/10ul.yml
labsuite/config/containers/tipracks/200ul.yml
labsuite/config/containers/troughs/12.yml
labsuite/config/containers/tuberacks/15-50ml.yml
labsuite/config/containers/tuberacks/2000ul.yml
labsuite/config/containers/tuberacks/750ul.yml
labsuite/engine/__init__.py
labsuite/engine/commands.py
labsuite/engine/context.py
labsuite/engine/session.py
labsuite/labware/__init__.py
labsuite/labware/containers.py
labsuite/labware/deck.py
labsuite/labware/grid.py
labsuite/labware/liquids.py
labsuite/labware/microplates.py
labsuite/labware/mixtures.py
labsuite/labware/pipettes.py
labsuite/labware/reservoirs.py
labsuite/labware/tipracks.py
labsuite/labware/tuberacks.py
tests/__init__.py
tests/labsuite/__init__.py
tests/labsuite/compilers/__init__.py
tests/labsuite/compilers/test_pfusx.py
tests/labsuite/engine/__init__.py
tests/labsuite/engine/test_commands.py
tests/labsuite/engine/test_session.py
tests/labsuite/labware/__init__.py
tests/labsuite/labware/test_containers.py
tests/labsuite/labware/test_deck.py
tests/labsuite/labware/test_grid.py
tests/labsuite/labware/test_microplates.py
tests/labsuite/labware/test_pipettes.py
tests/labsuite/labware/test_reservoirs.py
tests/labsuite/labware/test_tipracks.py