Metadata-Version: 1.0
Name: labsuite
Version: 0.4
Summary: A suite of tools for portable automated scientific protocols.
Home-page: http://opentrons.com
Author: OpenTrons
Author-email: info@opentrons.com
License: UNKNOWN
Platform: UNKNOWN
